comping/__init__.py
comping/base.py
comping/strategies/__init__.py
comping/strategies/blind_update/__init__.py
comping/strategies/blind_update/cumulative_update.py
comping/strategies/blind_update/sliding_update.py
comping/strategies/informed_update/distribution_based/__init__.py
comping/strategies/informed_update/performance_based/__init__.py
comping/strategies/informed_update/performance_based/ddm.py
comping/utils/__init__.py
comping/utils/adapter.py
comping/utils/data_handler.py
comping/utils/detectors.py
comping-0.1.1.dist-info/METADATA
comping-0.1.1.dist-info/WHEEL
comping-0.1.1.dist-info/top_level.txt
comping-0.1.1.dist-info/RECORD
