Metadata-Version: 2.4
Name: comping
Version: 0.1.1
Summary: MLOps concept drift detection & adaptation library
Author-email: Comping AI Team <gj.kim@comping.ai>
License: Apache-2.0
Project-URL: Homepage, https://comping.ai
Project-URL: Repository, https://github.com/technometrics/comping
Requires-Python: >=3.8
Requires-Dist: numpy>=1.20.0
Requires-Dist: pandas>=1.3.0
Requires-Dist: scikit-learn>=1.0.0
